<annotation>
	<folder>blueBackgroundNoBase</folder>
	<filename>eframe43.jpg</filename>
	<path>C:\Users\kyle_\development\object_detection_demo\data\raw\KyleImages\blueBackgroundNoBase\eframe43.jpg</path>
	<source>
		<database>Unknown</database>
	</source>
	<size>
		<width>800</width>
		<height>600</height>
		<depth>3</depth>
	</size>
	<segmented>0</segmented>
	<object>
		<name>tip</name>
		<pose>Unspecified</pose>
		<truncated>0</truncated>
		<difficult>0</difficult>
		<bndbox>
			<xmin>146</xmin>
			<ymin>230</ymin>
			<xmax>259</xmax>
			<ymax>342</ymax>
		</bndbox>
	</object>
</annotation>
