<annotation>
	<folder>redBackgroundRedBase</folder>
	<filename>aframe138.jpg</filename>
	<path>C:\Users\11007\vision\object_detection_demo\data\raw\FionaImages\redBackgroundRedBase\aframe138.jpg</path>
	<source>
		<database>Unknown</database>
	</source>
	<size>
		<width>800</width>
		<height>600</height>
		<depth>3</depth>
	</size>
	<segmented>0</segmented>
	<object>
		<name>tip</name>
		<pose>Unspecified</pose>
		<truncated>0</truncated>
		<difficult>0</difficult>
		<bndbox>
			<xmin>522</xmin>
			<ymin>467</ymin>
			<xmax>638</xmax>
			<ymax>587</ymax>
		</bndbox>
	</object>
</annotation>
