<annotation>
	<folder>shadeBlueBackgroundNoBase</folder>
	<filename>lframe162.jpg</filename>
	<path>C:\Users\kyle_\development\object_detection_demo\data\raw\newAssignmentKyle\shadeBlueBackgroundNoBase\lframe162.jpg</path>
	<source>
		<database>Unknown</database>
	</source>
	<size>
		<width>800</width>
		<height>600</height>
		<depth>3</depth>
	</size>
	<segmented>0</segmented>
	<object>
		<name>tip</name>
		<pose>Unspecified</pose>
		<truncated>0</truncated>
		<difficult>0</difficult>
		<bndbox>
			<xmin>318</xmin>
			<ymin>429</ymin>
			<xmax>426</xmax>
			<ymax>538</ymax>
		</bndbox>
	</object>
</annotation>
